wednesday/6502js_cpu.js
wednesday/__init__.py
wednesday/bridge/__init__.py
wednesday/bridge/applepy.py
wednesday/bridge/arbne.py
wednesday/bridge/jsnes.py
wednesday/bridge/py3nes.py
wednesday/bridge/py65.py
wednesday/bridge/pyntendo.py
wednesday/bridge/t6502js.py
wednesday/cpu_6502_draft.py
wednesday/cpu_6502_spec.py
wednesday/emulators/__init__.py
wednesday/emulators/applepy/__init__.py
wednesday/emulators/applepy/cpu.py
wednesday/emulators/arbae/__init__.py
wednesday/emulators/arbae/cpu.py
wednesday/emulators/py3nes/__init__.py
wednesday/emulators/py3nes/addressing.py
wednesday/emulators/py3nes/apu.py
wednesday/emulators/py3nes/cpu.py
wednesday/emulators/py3nes/helpers.py
wednesday/emulators/py3nes/instructions/__init__.py
wednesday/emulators/py3nes/instructions/arithmetic_instructions.py
wednesday/emulators/py3nes/instructions/base_instructions.py
wednesday/emulators/py3nes/instructions/bit_instructions.py
wednesday/emulators/py3nes/instructions/combination_instructions.py
wednesday/emulators/py3nes/instructions/generic_instructions.py
wednesday/emulators/py3nes/instructions/instructions.py
wednesday/emulators/py3nes/instructions/jump_instructions.py
wednesday/emulators/py3nes/instructions/load_instructions.py
wednesday/emulators/py3nes/instructions/store_instructions.py
wednesday/emulators/py3nes/main.py
wednesday/emulators/py3nes/memory_owner.py
wednesday/emulators/py3nes/ppu.py
wednesday/emulators/py3nes/ram.py
wednesday/emulators/py3nes/rom.py
wednesday/emulators/py3nes/status.py
wednesday/generate.py
wednesday/jsnes_cpu.js
wednesday/ports.py
wednesday/tests/__init__.py
wednesday/tests/applepy_cpu_test.py
wednesday/tests/arbne_cpu_test.py
wednesday/tests/fixtures/nestest/nestest.log
wednesday/tests/fixtures/nestest/nestest_noclock.log
wednesday/tests/fixtures/nestest/nestest_regonly.log
wednesday/tests/jsnes_cpu_test.py
wednesday/tests/machine_language_for_beginners_test.py
wednesday/tests/mapper_0_NROM_test.py
wednesday/tests/mapper_1_MMC1_test.py
wednesday-0.0.2.dist-info/METADATA
wednesday-0.0.2.dist-info/WHEEL
wednesday-0.0.2.dist-info/RECORD
